<oai_dc:dc xmlns:oai_dc="http://www.openarchives.org/OAI/2.0/oai_dc/" xmlns:doc="http://www.lyncode.com/xoai" xmlns:xsi="http://www.w3.org/2001/XMLSchema-instance" xmlns:dc="http://purl.org/dc/elements/1.1/" xsi:schemaLocation="http://www.openarchives.org/OAI/2.0/oai_dc/ http://www.openarchives.org/OAI/2.0/oai_dc.xsd">
  <dc:title>Breeding strategies for resistance to the rusts of wheat</dc:title>
  <dc:creator>Simmonds, N.W.</dc:creator>
  <dc:creator>Rajaram, S.</dc:creator>
  <dc:subject>Plant breeding</dc:subject>
  <dc:subject>Disease control</dc:subject>
  <dc:subject>Testing</dc:subject>
  <dc:subject>Rusts</dc:subject>
  <dc:subject>Genetic stability</dc:subject>
  <dc:subject>Chromosomes</dc:subject>
  <dc:subject>Genes</dc:subject>
  <dc:subject>Site factors</dc:subject>
  <dc:subject>Breeding</dc:subject>
  <dc:subject>Pathogenicity</dc:subject>
  <dc:subject>Cereals</dc:subject>
  <dc:subject>Buffers</dc:subject>
  <dc:subject>Plant diseases</dc:subject>
  <dc:subject>Triticales</dc:subject>
  <dc:subject>Leaves</dc:subject>
  <dc:subject>Wheats</dc:subject>
  <dc:subject>Puccinia</dc:subject>
  <dc:subject>Yields</dc:subject>
  <dc:subject>Stems</dc:subject>
  <dc:subject>Fungus control</dc:subject>
  <dc:subject>Natural distribution</dc:subject>
  <dc:subject>Trials</dc:subject>
  <dc:description>The International Workshop on Breeding Strategies for Resistance to the Rusts of Wheat was held al CIMMYT, Mexico June 29-Jul 1, 1987. It brought together an eminent panel of internationally recognized specialists who reviewed the current situation and defined a broad breeding strategy to incorporate the necessary level of resistance to control leaf, stem, and yellow rusts. Contributions deal with the following topics: the role of specific genes, diversity, and the use of polygenic, partial, and durable resistances; disease management through variety mixtures; and current approaches al CIMMYT in breeding wheat for rust resistance</dc:description>
  <dc:date>2012-01-06T05:14:14Z</dc:date>
  <dc:date>2012-01-06T05:14:14Z</dc:date>
  <dc:pubDate>1988</dc:pubDate>
  <dc:type>Books and monographs</dc:type>
  <dc:isbn>968-6127-23-2</dc:isbn>
  <dc:identifier>http://hdl.handle.net/10883/1103</dc:identifier>
  <dc:language>English</dc:language>
  <dc:rights>CIMMYT manages Intellectual Assets as International Public Goods. The user is free to download, print, store and share this work. In case you want to translate or create any other derivative work and share or distribute such translation/derivative work, please contact CIMMYT-Knowledge-Center@cgiar.org indicating the work you want to use and the kind of use you intend; CIMMYT will contact you with the sutable license for that purpose.</dc:rights>
  <dc:publisher>CIMMYT</dc:publisher>
  <dc:geotag>Mexico</dc:geotag>
  <dc:geonames>http://sws.geonames.org/3996063</dc:geonames>
  <dc:domainid>10883</dc:domainid>
  <dc:cdocid>1103</dc:cdocid>
  <dc:apiid>10883_1103</dc:apiid>
  <dc:cset>com_10883_1</dc:cset>
  <dc:setid>1403840553</dc:setid>
  <dc:cset>col_10883_8</dc:cset>
  <dc:setid>403613917</dc:setid>
  <dc:cset>col_10883_2</dc:cset>
  <dc:setid>403613911</dc:setid>
  <dc:updated_date>2016-01-22T23:05:41Z</dc:updated_date>
  <dc:handler>http://repository.cimmyt.org/oai/request</dc:handler>
</oai_dc:dc>