<oai_dc:dc xmlns:oai_dc="http://www.openarchives.org/OAI/2.0/oai_dc/" xmlns:doc="http://www.lyncode.com/xoai" xmlns:xsi="http://www.w3.org/2001/XMLSchema-instance" xmlns:dc="http://purl.org/dc/elements/1.1/" xsi:schemaLocation="http://www.openarchives.org/OAI/2.0/oai_dc/ http://www.openarchives.org/OAI/2.0/oai_dc.xsd">
  <dc:title>The first flight over El Batan with a fix wings UAV</dc:title>
  <dc:contributor>CIMMYT</dc:contributor>
  <dc:contributor>CIMMYT</dc:contributor>
  <dc:subject>Equipment</dc:subject>
  <dc:subject>Drones</dc:subject>
  <dc:description>The first flight over El Batan</dc:description>
  <dc:description>Tattaris, M.</dc:description>
  <dc:description>Rodrigues, F.</dc:description>
  <dc:date>2015-11-05T17:21:09Z</dc:date>
  <dc:date>2015-11-05T17:21:09Z</dc:date>
  <dc:pubDate>2015</dc:pubDate>
  <dc:identifier>http://hdl.handle.net/10883/4614</dc:identifier>
  <dc:language>spa</dc:language>
  <dc:language>None</dc:language>
  <dc:rights>Creative Commons Attribution-NonCommercial-NoDerivatives 4.0 International ยง CIMMYT manages Intellectual Assets as International Public Goods. In case you want to make non-exclusive commercial use of this item or you want to adapt it in any manner and use such adaptation, please contact CIMMYT-Knowledge-Center@cgiar.org indicating the code/name of this item and the kind of use you intend; CIMMYT will contact you with the terms and conditions for such use.</dc:rights>
  <dc:rights>https://creativecommons.org/licenses/by-nc-nd/4.0/</dc:rights>
  <dc:format>MP4</dc:format>
  <dc:format>HQ</dc:format>
  <dc:domainid>10883</dc:domainid>
  <dc:cdocid>4614</dc:cdocid>
  <dc:apiid>10883_4614</dc:apiid>
  <dc:lexvo>http://lexvo.org/id/iso639-3/spa</dc:lexvo>
  <dc:cset>com_10883_4047</dc:cset>
  <dc:setid>1717216103</dc:setid>
  <dc:cset>col_10883_4049</dc:cset>
  <dc:setid>1846298820</dc:setid>
  <dc:updated_date>2015-05-27T20:22:55Z</dc:updated_date>
  <dc:handler>http://repository.cimmyt.org/oai/request</dc:handler>
</oai_dc:dc>